simpleDS/__init__.py
simpleDS/cosmo.py
simpleDS/delay_spectrum.py
simpleDS/parameter.py
simpleDS/utils.py
simpleDS/data/__init__.py
simpleDS/data/__init__.pyc
simpleDS/data/mwa_full_poll.uvh5
simpleDS/data/paper_antpos.txt
simpleDS/data/paper_test_file.uvh5
simpleDS/data/paper_test_file_2nd_time.uvh5
simpleDS/data/paper_test_file_k_units.uvh5
simpleDS/data/paper_test_file_uncalib_units.uvh5
simpleDS/data/test_multiple_pol.beamfits
simpleDS/data/test_paper_pI.beamfits
simpleDS/data/test_redundant_array.beamfits
simpleDS/data/test_redundant_array_odd_file.uvh5
simpleDS/data/test_redundant_noise_data.uvh5
simpleDS/data/test_two_pol_array.uvfits
simpleDS/data/test_two_pol_array.uvh5
simpleDS/data/__pycache__/__init__.cpython-36.pyc
simpleDS/data/__pycache__/__init__.cpython-37.pyc
simpleDS/data/__pycache__/__init__.cpython-38.pyc
simpleDS/data/__pycache__/__init__.cpython-39.pyc
simpleDS/tests/__init__.py
simpleDS/tests/conftest.py
simpleDS/tests/test_cosmo.py
simpleDS/tests/test_delay_spectrum.py
simpleDS/tests/test_io.py
simpleDS/tests/test_parameter.py
simpleDS/tests/test_utils.py
simple_delay_spectrum-2.0.1.data/scripts/read_paper_miriad.py
simple_delay_spectrum-2.0.1.data/scripts/test_coverage.sh
simple_delay_spectrum-2.0.1.dist-info/LICENSE
simple_delay_spectrum-2.0.1.dist-info/METADATA
simple_delay_spectrum-2.0.1.dist-info/WHEEL
simple_delay_spectrum-2.0.1.dist-info/top_level.txt
simple_delay_spectrum-2.0.1.dist-info/RECORD
