Metadata-Version: 2.1
Name: simple-delay-spectrum
Version: 2.0.1
Summary: A Simple Delay Spectrum calculator for radio interferometers. 
Author: rasg-affiliates
License: BSD
Classifier: Development Status :: 4 - Beta
Classifier: Intended Audience :: Science/Research
Classifier: License :: OSI Approved :: BSD License
Classifier: Programming Language :: Python :: 3.8
Classifier: Programming Language :: Python :: 3.9
Classifier: Programming Language :: Python :: 3.10
Classifier: Topic :: Scientific/Engineering :: Astronomy
License-File: LICENSE
Requires-Dist: numpy (>=1.18)
Requires-Dist: astropy (>=5.0.4)
Requires-Dist: scipy
Requires-Dist: pyuvdata (>=1.4.2)
Provides-Extra: all
Requires-Dist: astropy-healpix ; extra == 'all'
Requires-Dist: pytest ; extra == 'all'
Requires-Dist: pytest-cov ; extra == 'all'
Provides-Extra: healpix
Requires-Dist: astropy-healpix ; extra == 'healpix'
